{"updated":"2026-06-01T06:15:39Z","quotes":{"000660.KS":{"price":2363000.0,"pct":3.23,"cur":"KRW"},"005380.KS":{"price":755000.0,"pct":11.52,"cur":"KRW"},"005930.KS":{"price":349000.0,"pct":16.53,"cur":"KRW"},"2454.TW":{"price":4555.0,"pct":5.68,"cur":"TWD"},"3529.TWO":{"price":3280.0,"pct":-3.81,"cur":"TWD"},"4062.T":{"price":21735.0,"pct":-5.5,"cur":"JPY"},"6762.T":{"price":4094.0,"pct":-0.34,"cur":"JPY"},"ATS.VI":{"price":141.0,"pct":0.57,"cur":"EUR"},"BRN.AX":{"price":0.17,"pct":9.68,"cur":"AUD"},"COH.AX":{"price":101.19,"pct":3.89,"cur":"AUD"},"WBT.AX":{"price":7.17,"pct":-2.45,"cur":"AUD"}}}