{"updated":"2026-06-08T03:05:07Z","quotes":{"000660.KS":{"price":2070000.0,"pct":-9.92,"cur":"KRW"},"005380.KS":{"price":655000.0,"pct":-6.43,"cur":"KRW"},"005930.KS":{"price":315500.0,"pct":-10.24,"cur":"KRW"},"2454.TW":{"price":4030.0,"pct":-6.28,"cur":"TWD"},"3529.TWO":{"price":3180.0,"pct":-7.42,"cur":"TWD"},"4062.T":{"price":17335.0,"pct":-7.6,"cur":"JPY"},"6762.T":{"price":3715.0,"pct":-9.63,"cur":"JPY"},"ATS.VI":{"price":133.2,"pct":-6.33,"cur":"EUR"},"BRN.AX":{"price":0.19,"pct":-5.0,"cur":"AUD"},"COH.AX":{"price":100.45,"pct":5.63,"cur":"AUD"},"WBT.AX":{"price":7.55,"pct":5.59,"cur":"AUD"}}}